pointpats/__init__.py
pointpats/centrography.py
pointpats/distance_statistics.py
pointpats/geometry.py
pointpats/kde.py
pointpats/pointpattern.py
pointpats/process.py
pointpats/quadrat_statistics.py
pointpats/random.py
pointpats/spacetime.py
pointpats/util.py
pointpats/window.py
pointpats/tests/__init__.py
pointpats/tests/test_centrography.py
pointpats/tests/test_distance_statistics.py
pointpats/tests/test_ellipse.py
pointpats/tests/test_kde.py
pointpats/tests/test_pointpattern.py
pointpats/tests/test_quadrat_statistics.py
pointpats/tests/test_spacetime.py
pointpats-2.5.2.dist-info/licenses/LICENSE.txt
pointpats-2.5.2.dist-info/METADATA
pointpats-2.5.2.dist-info/WHEEL
pointpats-2.5.2.dist-info/top_level.txt
pointpats-2.5.2.dist-info/RECORD
