Metadata-Version: 2.4
Name: pointpats
Version: 2.5.2
Summary: Methods and Functions for planar point pattern analysis
Author-email: Serge Rey <sjsrey@gmail.com>, Hu Shao <shaohutiger@gmail.com>
Maintainer: pysal contributors
License: BSD 3-Clause
Project-URL: Home, https://github.com/pysal/pointpats/
Project-URL: Repository, https://github.com/pysal/pointpats
Keywords: spatial statistics, point patterns
Classifier: Programming Language :: Python :: 3
Classifier: License :: OSI Approved :: BSD License
Classifier: Operating System :: OS Independent
Classifier: Intended Audience :: Science/Research
Classifier: Topic :: Scientific/Engineering :: GIS
Requires-Python: >=3.10
License-File: LICENSE.txt
Requires-Dist: libpysal>=4.8
Requires-Dist: geopandas>=0.12
Requires-Dist: matplotlib>=3.6
Requires-Dist: numpy>=1.24
Requires-Dist: pandas!=1.5.0,>=1.4
Requires-Dist: scipy>=1.10
Requires-Dist: shapely>=2
Provides-Extra: dev
Requires-Dist: pre-commit; extra == "dev"
Provides-Extra: docs
Requires-Dist: nbsphinx; extra == "docs"
Requires-Dist: numpydoc; extra == "docs"
Requires-Dist: pandoc; extra == "docs"
Requires-Dist: sphinx; extra == "docs"
Requires-Dist: sphinxcontrib-bibtex; extra == "docs"
Requires-Dist: sphinx_bootstrap_theme; extra == "docs"
Requires-Dist: mkdocs-jupyter; extra == "docs"
Requires-Dist: myst-parser; extra == "docs"
Provides-Extra: tests
Requires-Dist: codecov; extra == "tests"
Requires-Dist: coverage; extra == "tests"
Requires-Dist: folium; extra == "tests"
Requires-Dist: mapclassify; extra == "tests"
Requires-Dist: pytest; extra == "tests"
Requires-Dist: pytest-mpl; extra == "tests"
Requires-Dist: pytest-cov; extra == "tests"
Requires-Dist: scikit-learn>=1.2; extra == "tests"
Requires-Dist: statsmodels; extra == "tests"
Requires-Dist: watermark; extra == "tests"
Dynamic: license-file
